pymonitors/__init__.py
pymonitors/py.typed
pymonitors/common/__init__.py
pymonitors/common/monitor.py
pymonitors/common/os_detector.py
pymonitors/common/os_names.py
pymonitors/common/strategies.py
pymonitors/common/strategies_map.py
pymonitors/res/script.ps1
pymonitors/strategies/__init__.py
pymonitors/strategies/appkit_strategy.py
pymonitors/strategies/mswindows_strategy.py
pymonitors/strategies/strategy.py
pymonitors/strategies/xrandr_strategy.py
pymonitors-1.0.2.dist-info/LICENSE
pymonitors-1.0.2.dist-info/METADATA
pymonitors-1.0.2.dist-info/WHEEL
pymonitors-1.0.2.dist-info/top_level.txt
pymonitors-1.0.2.dist-info/RECORD
