Metadata-Version: 2.1
Name: pymonitors
Version: 1.0.2
Summary: PyMonitors: a Python library to obtain info about available screens (monitors).
Home-page: https://github.com/cloudstrife9999/pymonitors
Author: Emanuele Uliana
Author-email: vw@dicelab-rhul.org
License: GNU3
Classifier: Programming Language :: Python :: 3
Classifier: Programming Language :: Python :: 3.10
Classifier: Programming Language :: Python :: 3.11
Classifier: Programming Language :: Python :: 3 :: Only
Classifier: Development Status :: 4 - Beta
Classifier: License :: OSI Approved :: GNU General Public License v3 (GPLv3)
Classifier: Operating System :: OS Independent
License-File: LICENSE
Requires-Dist: pyjoptional (>=1.1.2)
Requires-Dist: wheel
